libname/__init__.py
libname/fastapiwrapper.py
gasconsumption-0.0.8.dist-info/METADATA
gasconsumption-0.0.8.dist-info/WHEEL
gasconsumption-0.0.8.dist-info/top_level.txt
gasconsumption-0.0.8.dist-info/RECORD
